{"name":"build-javascript","namedChunkGroups":{"polyfill":{"name":"polyfill","assets":[{"name":"webpack-runtime-387b570c2b7ca2fa7154.js","size":3918},{"name":"polyfill-8c0e31d1812733570f28.js","size":85830}],"filteredAssets":0,"assetsSize":89748,"filteredAuxiliaryAssets":2,"auxiliaryAssetsSize":223609},"app":{"name":"app","assets":[{"name":"webpack-runtime-387b570c2b7ca2fa7154.js","size":3918},{"name":"framework-653b4fcd2d62f8f12dca.js","size":129722},{"name":"styles.b7ded27e23a8dcab9f07.css","size":5316},{"name":"app-8760d8cf263e1da1d972.js","size":69549}],"filteredAssets":0,"assetsSize":208505,"filteredAuxiliaryAssets":3,"auxiliaryAssetsSize":655750},"component---src-pages-404-js":{"name":"component---src-pages-404-js","assets":[{"name":"component---src-pages-404-js-5355a456f36205615eb4.js","size":796}],"filteredAssets":0,"assetsSize":796,"filteredAuxiliaryAssets":1,"auxiliaryAssetsSize":1886},"component---src-pages-index-js":{"name":"component---src-pages-index-js","assets":[{"name":"cb1608f2-66edcb032e0a23287414.js","size":817},{"name":"a9a7754c-62aea5e32668c8edb371.js","size":2728},{"name":"component---src-pages-index-js-71808aade0775613856e.js","size":60266}],"filteredAssets":0,"assetsSize":63811,"filteredAuxiliaryAssets":3,"auxiliaryAssetsSize":1428422}},"assetsByChunkName":{"polyfill":["webpack-runtime-387b570c2b7ca2fa7154.js","polyfill-8c0e31d1812733570f28.js"],"app":["webpack-runtime-387b570c2b7ca2fa7154.js","framework-653b4fcd2d62f8f12dca.js","styles.b7ded27e23a8dcab9f07.css","app-8760d8cf263e1da1d972.js"],"component---src-pages-404-js":["component---src-pages-404-js-5355a456f36205615eb4.js"],"component---src-pages-index-js":["cb1608f2-66edcb032e0a23287414.js","a9a7754c-62aea5e32668c8edb371.js","component---src-pages-index-js-71808aade0775613856e.js"]},"childAssetsByChunkName":{}}